compressedlogger/__init__.py
compressedlogger/compressedlogger.py
compressedlogger-0.3.4.dist-info/AUTHORS.rst
compressedlogger-0.3.4.dist-info/LICENSE
compressedlogger-0.3.4.dist-info/METADATA
compressedlogger-0.3.4.dist-info/WHEEL
compressedlogger-0.3.4.dist-info/top_level.txt
compressedlogger-0.3.4.dist-info/RECORD
