Metadata-Version: 2.1
Name: compressedlogger
Version: 0.3.4
Summary: LoggingHandler to move logs into gziped archives in a smart way
Home-page: UNKNOWN
Author: Kai Friedrich
License: MIT license
Keywords: compressedlogger
Platform: UNKNOWN
Classifier: Development Status :: 4 - Beta
Classifier: Intended Audience :: Developers
Classifier: License :: OSI Approved :: MIT License
Classifier: Natural Language :: English
Classifier: Programming Language :: Python :: 3
Classifier: Programming Language :: Python :: 3.5
Classifier: Programming Language :: Python :: 3.6
Classifier: Programming Language :: Python :: 3.7
Classifier: Programming Language :: Python :: 3.8
Requires-Python: >=3.5
